time_utils/__init__.py
time_utils/time_utils.py
time_utils-1.0.1.dist-info/LICENSE
time_utils-1.0.1.dist-info/METADATA
time_utils-1.0.1.dist-info/WHEEL
time_utils-1.0.1.dist-info/top_level.txt
time_utils-1.0.1.dist-info/RECORD
