Metadata-Version: 2.1
Name: time-utils
Version: 1.0.1
Summary: Helper class to time python processes
Home-page: https://github.com/hannaj06/time_utils
Author: Joe Hanna
License: UNKNOWN
Platform: UNKNOWN
Classifier: Programming Language :: Python :: 3
Classifier: License :: OSI Approved :: MIT License
Classifier: Operating System :: OS Independent
